git_clone/__init__.py
git_clone/git_clone.py
git_clone-1.0.6.dist-info/METADATA
git_clone-1.0.6.dist-info/WHEEL
git_clone-1.0.6.dist-info/entry_points.txt
git_clone-1.0.6.dist-info/top_level.txt
git_clone-1.0.6.dist-info/RECORD
